agml/__init__.py
agml/framework.py
agml/io.py
agml/_assets/detector_benchmarks.json
agml/_assets/iNatAg-mini_public_datasources.json
agml/_assets/iNatAg-mini_source_citations.json
agml/_assets/iNatAg_public_datasources.json
agml/_assets/iNatAg_source_citations.json
agml/_assets/model_benchmarks.json
agml/_assets/public_datasources.json
agml/_assets/shape_info.pickle
agml/_assets/source_citations.json
agml/_assets/viz_colormaps.json
agml/_internal/__init__.py
agml/_internal/preprocess.py
agml/_internal/s3internal.py
agml/_internal/utils.py
agml/backend/__init__.py
agml/backend/config.py
agml/backend/experimental.py
agml/backend/random.py
agml/backend/tftorch.py
agml/data/__init__.py
agml/data/builder.py
agml/data/experimental.py
agml/data/image_loader.py
agml/data/loader.py
agml/data/manager.py
agml/data/metadata.py
agml/data/multi_loader.py
agml/data/object.py
agml/data/point_cloud.py
agml/data/public.py
agml/data/tools.py
agml/data/exporters/__init__.py
agml/data/exporters/tensorflow.py
agml/data/exporters/yolo.py
agml/data/extensions/__init__.py
agml/data/extensions/cvat.py
agml/data/managers/__init__.py
agml/data/managers/resize.py
agml/data/managers/training.py
agml/data/managers/transform_helpers.py
agml/data/managers/transforms.py
agml/models/__init__.py
agml/models/base.py
agml/models/benchmarks.py
agml/models/classification.py
agml/models/detection.py
agml/models/detector.py
agml/models/losses.py
agml/models/preprocessing.py
agml/models/segmentation.py
agml/models/system_utils.py
agml/models/tools.py
agml/models/extensions/__init__.py
agml/models/extensions/ultralytics.py
agml/models/legacy/__init__.py
agml/models/legacy/classification_efficientnet.py
agml/models/legacy/detection_efficientdet.py
agml/models/legacy/segmentation_deeplab.py
agml/models/metrics/__init__.py
agml/models/metrics/accuracy.py
agml/models/metrics/map.py
agml/models/training/__init__.py
agml/models/training/basic_trainers.py
agml/synthetic/__init__.py
agml/synthetic/compilation.py
agml-0.7.4.dist-info/METADATA
agml-0.7.4.dist-info/WHEEL
agml-0.7.4.dist-info/licenses/AUTHORS
agml-0.7.4.dist-info/licenses/LICENSE
agml-0.7.4.dist-info/RECORD
