Metadata-Version: 2.4
Name: agml
Version: 0.7.4
Summary: A comprehensive library for agricultural deep learning
Author-email: UC Davis Plant AI and Biophysics Lab <jmearles@ucdavis.edu>
Maintainer-email: Amogh Joshi <amnjoshi@ucdavis.edu>
License: Apache 2.0
License-File: AUTHORS
License-File: LICENSE
Classifier: Development Status :: 4 - Beta
Classifier: Intended Audience :: Developers
Classifier: Programming Language :: Python
Classifier: Programming Language :: Python :: 3
Classifier: Programming Language :: Python :: 3 :: Only
Classifier: Programming Language :: Python :: 3.8
Classifier: Programming Language :: Python :: 3.9
Classifier: Programming Language :: Python :: 3.10
Classifier: Programming Language :: Python :: 3.11
Classifier: Programming Language :: Python :: 3.12
Classifier: Programming Language :: Python :: 3.13
Classifier: Topic :: Documentation
Classifier: Topic :: Scientific/Engineering
Classifier: Topic :: Software Development
Classifier: Topic :: Utilities
Classifier: Typing :: Typed
Requires-Python: <3.12,>=3.8
Requires-Dist: albumentations>=1.4.18
Requires-Dist: dict2xml>=1.7.6
Requires-Dist: ipywidgets>=8.1.5
Requires-Dist: matplotlib>=3.7.5
Requires-Dist: numpy>=1.24.4
Requires-Dist: opencv-python-headless>=4.10.0.84
Requires-Dist: opencv-python>=4.10.0.84
Requires-Dist: pyyaml>=6.0.2
Requires-Dist: requests>=2.0.0
Requires-Dist: rich>=14.0.0
Requires-Dist: scikit-learn>=1.3.2
Requires-Dist: tqdm>=4.67.0
